rio_pmtiles/__init__.py
rio_pmtiles/worker.py
rio_pmtiles/scripts/__init__.py
rio_pmtiles/scripts/cli.py
rio_pmtiles-1.2.0.dist-info/licenses/LICENSE
rio_pmtiles-1.2.0.dist-info/METADATA
rio_pmtiles-1.2.0.dist-info/WHEEL
rio_pmtiles-1.2.0.dist-info/entry_points.txt
rio_pmtiles-1.2.0.dist-info/top_level.txt
rio_pmtiles-1.2.0.dist-info/RECORD
