Metadata-Version: 2.4
Name: rio-pmtiles
Version: 1.2.0
Summary: A Rasterio plugin command that exports PMTiles
Home-page: https://github.com/protomaps/PMTiles
Author: Brandon Liu
Author-email: brandon@protomaps.com
License: MIT
Requires-Python: >=3.7.0
License-File: LICENSE
Requires-Dist: click
Requires-Dist: cligj>=0.5
Requires-Dist: mercantile
Requires-Dist: pmtiles~=3.0
Requires-Dist: pyroaring~=1.0
Requires-Dist: rasterio~=1.0
Requires-Dist: shapely~=2.0.0
Requires-Dist: supermercado
Requires-Dist: tqdm~=4.0
Provides-Extra: test
Requires-Dist: coveralls; extra == "test"
Requires-Dist: pytest; extra == "test"
Requires-Dist: pytest-cov; extra == "test"
Dynamic: author
Dynamic: author-email
Dynamic: description
Dynamic: home-page
Dynamic: keywords
Dynamic: license
Dynamic: license-file
Dynamic: provides-extra
Dynamic: requires-dist
Dynamic: requires-python
Dynamic: summary
